happytrans
